{
    "Version": "1.2",
    "Data": {
        "Source": "c:\\program files\\microsoft visual studio\\2022\\community\\vc\\tools\\msvc\\14.36.32532\\include\\xthreads.h",
        "ProvidedModule": "",
        "Includes": [
            "c:\\program files\\microsoft visual studio\\2022\\community\\vc\\tools\\msvc\\14.36.32532\\include\\yvals_core.h",
            "c:\\program files\\microsoft visual studio\\2022\\community\\vc\\tools\\msvc\\14.36.32532\\include\\vcruntime.h",
            "c:\\program files\\microsoft visual studio\\2022\\community\\vc\\tools\\msvc\\14.36.32532\\include\\sal.h",
            "c:\\program files\\microsoft visual studio\\2022\\community\\vc\\tools\\msvc\\14.36.32532\\include\\concurrencysal.h",
            "c:\\program files\\microsoft visual studio\\2022\\community\\vc\\tools\\msvc\\14.36.32532\\include\\vadefs.h",
            "c:\\program files\\microsoft visual studio\\2022\\community\\vc\\tools\\msvc\\14.36.32532\\include\\xkeycheck.h"
        ],
        "ImportedModules": [],
        "ImportedHeaderUnits": [
            {
                "Header": "c:\\program files\\microsoft visual studio\\2022\\community\\vc\\tools\\msvc\\14.36.32532\\include\\climits",
                "BMI": "C:\\Users\\Michał\\source\\repos\\89863361-gr21-repo\\Projekt\\Snake_Game\\Snake_Game\\x64\\Debug\\climits_64781F34D8E15599.ifc.dt"
            },
            {
                "Header": "c:\\program files\\microsoft visual studio\\2022\\community\\vc\\tools\\msvc\\14.36.32532\\include\\xtimec.h",
                "BMI": "C:\\Users\\Michał\\source\\repos\\89863361-gr21-repo\\Projekt\\Snake_Game\\Snake_Game\\x64\\Debug\\xtimec.h_34BD8570EE06CFA8.ifc.dt"
            }
        ]
    }
}